{
  "run": [
    {
      "filePath": "/webapp/test/testFLPService.html",
      "previewMode": 0,
      "dataMode": 0,
      "workspace": "withoutWorkspace",
      "ui5ActiveVersion": null,
      "ui5VerSource": null,
      "isDefaultVersion": 0,
      "urlParameters": [],
      "hashParameter": "",
      "backendSystem": [],
      "urlParametersNotNeeded": false,
      "_metadata": {
        "id": 6681633,
        "runnerId": "webapprunner",
        "displayName": "Configuration",
        "lastRunTimeStamp": 1482135200874
      }
    }
  ]
}